pyloid_builder/__Init__.py
pyloid_builder/optimize.py
pyloid_builder/package.py
pyloid_builder/pyinstaller.py
pyloid_builder-0.4.1.dist-info/METADATA
pyloid_builder-0.4.1.dist-info/WHEEL
pyloid_builder-0.4.1.dist-info/RECORD
