Metadata-Version: 2.4
Name: pyloid-builder
Version: 0.4.1
Summary: Pyloid Builder is a tool for building Pyloid applications with PyInstaller.
Author-email: hyeonho cho <111675679+aesthetics-of-record@users.noreply.github.com>
Requires-Python: >=3.9
Requires-Dist: pyinstaller>=6.16.0
Requires-Dist: rich>=14.1.0
